Workbook

Sheet Assumptions
A1: Parameter | B1: Value | C1: Unit | D1: Source / Note
A2: Gemini API pricing (2026)
A3: Gemini 2.5 Flash — input price per 1M tokens | B3: 0.3 | C3: $ | D3: Source: Google AI pricing, 2026-04
A4: Gemini 2.5 Flash — output price per 1M tokens | B4: 2.5 | C4: $ | D4: Source: Google AI pricing, 2026-04
A5: Gemini 2.5 Pro — input price per 1M tokens | B5: 1.25 | C5: $ | D5: Source: Google AI pricing, 2026-04
A6: Gemini 2.5 Pro — output price per 1M tokens | B6: 10 | C6: $ | D6: Source: Google AI pricing, 2026-04
A8: Video token counts (per Gemini docs)
A9: Video tokens per second (video + audio combined) | B9: 263 | C9: tokens | D9: Source: Gemini API docs — video @ 1 FPS default
A10: Prompt tokens — base pass (system + instruction) | B10: 3000 | C10: tokens | D10: Est. from lib/video/prompts.ts
A11: Prompt tokens — extended pass (system + instruction) | B11: 5000 | C11: tokens | D11: Est. from lib/video/analysis-extended-prompt.ts
A12: Output tokens — base pass (structured JSON) | B12: 5000 | C12: tokens | D12: Est. from typical final.json base section
A13: Output tokens — extended pass (structured JSON) | B13: 8000 | C13: tokens | D13: Est. from typical final.json extended section
A15: Infrastructure COGS per analysis
A16: Vercel Function compute cost per analysis | B16: 0.005 | C16: $ | D16: Est. at maxDuration=120s, 2GB mem
A17: Vercel Blob storage cost per analysis per month | B17: 0.001 | C17: $ | D17: ~30MB average × $0.023/GB/mo
A18: Egress / bandwidth cost per analysis | B18: 0.001 | C18: $ | D18: Video fetch to Gemini + result transfer
A19: Other variable overhead per analysis | B19: 0.005 | C19: $ | D19: Monitoring, logging, error tracking
A21: Pricing scenarios
A22: Price per credit ($/credit) | B22: 1 | C22: $ | D22: Single credit price. Retail bundles can add markup on top.
A23: Credits per Flash analysis | B23: 1 | C23: credits | D23: Base packaging
A24: Credits per Pro analysis | B24: 3 | C24: credits | D24: Pro charges 3x credits — still under 5% of production cost
A26: Fixed monthly overhead (outside COGS)
A27: Vercel base plan + Postgres + Blob | B27: 200 | C27: $/mo | D27: Neon + Vercel Pro baseline
A28: Monitoring + error tracking (Sentry etc) | B28: 80 | C28: $/mo | D28: Small team tier
A29: Salaries attributed (founder/contractor, amortized) | B29: 12000 | C29: $/mo | D29: 1 FTE at conservative rate
A30: Sales/Marketing spend per month | B30: 2000 | C30: $/mo | D30: Content, tools, ad experiments

Sheet Per Analysis
A1: Per-Analysis Cost Breakdown — Flash vs Pro by Video Length
A3: Video length (seconds) → | B3: 15 | C3: 30 | D3: 45 | E3: 60 | F3: 90 | G3: 120 | H3: 180
A4: GEMINI 2.5 FLASH
A5: Video tokens per pass | B5: =15*Assumptions!B9 | C5: =30*Assumptions!B9 | D5: =45*Assumptions!B9 | E5: =60*Assumptions!B9 | F5: =90*Assumptions!B9 | G5: =120*Assumptions!B9 | H5: =180*Assumptions!B9
A6: Base pass — total input tokens | B6: =B5+Assumptions!B10 | C6: =C5+Assumptions!B10 | D6: =D5+Assumptions!B10 | E6: =E5+Assumptions!B10 | F6: =F5+Assumptions!B10 | G6: =G5+Assumptions!B10 | H6: =H5+Assumptions!B10
A7: Base pass — input cost ($) | B7: =B6/1000000*Assumptions!B3 | C7: =C6/1000000*Assumptions!B3 | D7: =D6/1000000*Assumptions!B3 | E7: =E6/1000000*Assumptions!B3 | F7: =F6/1000000*Assumptions!B3 | G7: =G6/1000000*Assumptions!B3 | H7: =H6/1000000*Assumptions!B3
A8: Base pass — output cost ($) | B8: =Assumptions!B12/1000000*Assumptions!B4 | C8: =Assumptions!B12/1000000*Assumptions!B4 | D8: =Assumptions!B12/1000000*Assumptions!B4 | E8: =Assumptions!B12/1000000*Assumptions!B4 | F8: =Assumptions!B12/1000000*Assumptions!B4 | G8: =Assumptions!B12/1000000*Assumptions!B4 | H8: =Assumptions!B12/1000000*Assumptions!B4
A9: Extended pass — total input tokens | B9: =B5+Assumptions!B11 | C9: =C5+Assumptions!B11 | D9: =D5+Assumptions!B11 | E9: =E5+Assumptions!B11 | F9: =F5+Assumptions!B11 | G9: =G5+Assumptions!B11 | H9: =H5+Assumptions!B11
A10: Extended pass — input cost ($) | B10: =B9/1000000*Assumptions!B3 | C10: =C9/1000000*Assumptions!B3 | D10: =D9/1000000*Assumptions!B3 | E10: =E9/1000000*Assumptions!B3 | F10: =F9/1000000*Assumptions!B3 | G10: =G9/1000000*Assumptions!B3 | H10: =H9/1000000*Assumptions!B3
A11: Extended pass — output cost ($) | B11: =Assumptions!B13/1000000*Assumptions!B4 | C11: =Assumptions!B13/1000000*Assumptions!B4 | D11: =Assumptions!B13/1000000*Assumptions!B4 | E11: =Assumptions!B13/1000000*Assumptions!B4 | F11: =Assumptions!B13/1000000*Assumptions!B4 | G11: =Assumptions!B13/1000000*Assumptions!B4 | H11: =Assumptions!B13/1000000*Assumptions!B4
A12: LLM subtotal ($) | B12: =B7+B8+B10+B11 | C12: =C7+C8+C10+C11 | D12: =D7+D8+D10+D11 | E12: =E7+E8+E10+E11 | F12: =F7+F8+F10+F11 | G12: =G7+G8+G10+G11 | H12: =H7+H8+H10+H11
A13: Infrastructure COGS ($) | B13: =Assumptions!B16+Assumptions!B17+Assumptions!B18+Assumptions!B19 | C13: =Assumptions!B16+Assumptions!B17+Assumptions!B18+Assumptions!B19 | D13: =Assumptions!B16+Assumptions!B17+Assumptions!B18+Assumptions!B19 | E13: =Assumptions!B16+Assumptions!B17+Assumptions!B18+Assumptions!B19 | F13: =Assumptions!B16+Assumptions!B17+Assumptions!B18+Assumptions!B19 | G13: =Assumptions!B16+Assumptions!B17+Assumptions!B18+Assumptions!B19 | H13: =Assumptions!B16+Assumptions!B17+Assumptions!B18+Assumptions!B19
A14: TOTAL COGS per analysis — Flash ($) | B14: =B12+B13 | C14: =C12+C13 | D14: =D12+D13 | E14: =E12+E13 | F14: =F12+F13 | G14: =G12+G13 | H14: =H12+H13
A15: Revenue per analysis — Flash (1 credit × $/credit) | B15: =Assumptions!B22*Assumptions!B23 | C15: =Assumptions!B22*Assumptions!B23 | D15: =Assumptions!B22*Assumptions!B23 | E15: =Assumptions!B22*Assumptions!B23 | F15: =Assumptions!B22*Assumptions!B23 | G15: =Assumptions!B22*Assumptions!B23 | H15: =Assumptions!B22*Assumptions!B23
A16: Gross margin % — Flash | B16: =IFERROR((B15-B14)/B15,0) | C16: =IFERROR((C15-C14)/C15,0) | D16: =IFERROR((D15-D14)/D15,0) | E16: =IFERROR((E15-E14)/E15,0) | F16: =IFERROR((F15-F14)/F15,0) | G16: =IFERROR((G15-G14)/G15,0) | H16: =IFERROR((H15-H14)/H15,0)
A18: GEMINI 2.5 PRO
A19: Video tokens per pass | B19: =15*Assumptions!B9 | C19: =30*Assumptions!B9 | D19: =45*Assumptions!B9 | E19: =60*Assumptions!B9 | F19: =90*Assumptions!B9 | G19: =120*Assumptions!B9 | H19: =180*Assumptions!B9
A20: Base pass — total input tokens | B20: =B19+Assumptions!B10 | C20: =C19+Assumptions!B10 | D20: =D19+Assumptions!B10 | E20: =E19+Assumptions!B10 | F20: =F19+Assumptions!B10 | G20: =G19+Assumptions!B10 | H20: =H19+Assumptions!B10
A21: Base pass — input cost ($) | B21: =B20/1000000*Assumptions!B5 | C21: =C20/1000000*Assumptions!B5 | D21: =D20/1000000*Assumptions!B5 | E21: =E20/1000000*Assumptions!B5 | F21: =F20/1000000*Assumptions!B5 | G21: =G20/1000000*Assumptions!B5 | H21: =H20/1000000*Assumptions!B5
A22: Base pass — output cost ($) | B22: =Assumptions!B12/1000000*Assumptions!B6 | C22: =Assumptions!B12/1000000*Assumptions!B6 | D22: =Assumptions!B12/1000000*Assumptions!B6 | E22: =Assumptions!B12/1000000*Assumptions!B6 | F22: =Assumptions!B12/1000000*Assumptions!B6 | G22: =Assumptions!B12/1000000*Assumptions!B6 | H22: =Assumptions!B12/1000000*Assumptions!B6
A23: Extended pass — total input tokens | B23: =B19+Assumptions!B11 | C23: =C19+Assumptions!B11 | D23: =D19+Assumptions!B11 | E23: =E19+Assumptions!B11 | F23: =F19+Assumptions!B11 | G23: =G19+Assumptions!B11 | H23: =H19+Assumptions!B11
A24: Extended pass — input cost ($) | B24: =B23/1000000*Assumptions!B5 | C24: =C23/1000000*Assumptions!B5 | D24: =D23/1000000*Assumptions!B5 | E24: =E23/1000000*Assumptions!B5 | F24: =F23/1000000*Assumptions!B5 | G24: =G23/1000000*Assumptions!B5 | H24: =H23/1000000*Assumptions!B5
A25: Extended pass — output cost ($) | B25: =Assumptions!B13/1000000*Assumptions!B6 | C25: =Assumptions!B13/1000000*Assumptions!B6 | D25: =Assumptions!B13/1000000*Assumptions!B6 | E25: =Assumptions!B13/1000000*Assumptions!B6 | F25: =Assumptions!B13/1000000*Assumptions!B6 | G25: =Assumptions!B13/1000000*Assumptions!B6 | H25: =Assumptions!B13/1000000*Assumptions!B6
A26: LLM subtotal ($) | B26: =B21+B22+B24+B25 | C26: =C21+C22+C24+C25 | D26: =D21+D22+D24+D25 | E26: =E21+E22+E24+E25 | F26: =F21+F22+F24+F25 | G26: =G21+G22+G24+G25 | H26: =H21+H22+H24+H25
A27: Infrastructure COGS ($) | B27: =Assumptions!B16+Assumptions!B17+Assumptions!B18+Assumptions!B19 | C27: =Assumptions!B16+Assumptions!B17+Assumptions!B18+Assumptions!B19 | D27: =Assumptions!B16+Assumptions!B17+Assumptions!B18+Assumptions!B19 | E27: =Assumptions!B16+Assumptions!B17+Assumptions!B18+Assumptions!B19 | F27: =Assumptions!B16+Assumptions!B17+Assumptions!B18+Assumptions!B19 | G27: =Assumptions!B16+Assumptions!B17+Assumptions!B18+Assumptions!B19 | H27: =Assumptions!B16+Assumptions!B17+Assumptions!B18+Assumptions!B19
A28: TOTAL COGS per analysis — Pro ($) | B28: =B26+B27 | C28: =C26+C27 | D28: =D26+D27 | E28: =E26+E27 | F28: =F26+F27 | G28: =G26+G27 | H28: =H26+H27
A29: Revenue per analysis — Pro (3 credits × $/credit) | B29: =Assumptions!B22*Assumptions!B24 | C29: =Assumptions!B22*Assumptions!B24 | D29: =Assumptions!B22*Assumptions!B24 | E29: =Assumptions!B22*Assumptions!B24 | F29: =Assumptions!B22*Assumptions!B24 | G29: =Assumptions!B22*Assumptions!B24 | H29: =Assumptions!B22*Assumptions!B24
A30: Gross margin % — Pro | B30: =IFERROR((B29-B28)/B29,0) | C30: =IFERROR((C29-C28)/C29,0) | D30: =IFERROR((D29-D28)/D29,0) | E30: =IFERROR((E29-E28)/E29,0) | F30: =IFERROR((F29-F28)/F29,0) | G30: =IFERROR((G29-G28)/G29,0) | H30: =IFERROR((H29-H28)/H29,0)
A32: BLENDED (70% Flash / 30% Pro)
A33: Flash share | B33: 0.7
A34: Pro share | B34: 0.3
A35: Blended COGS per analysis ($) | B35: =B14*$B$33+B28*$B$34 | C35: =C14*$B$33+C28*$B$34 | D35: =D14*$B$33+D28*$B$34 | E35: =E14*$B$33+E28*$B$34 | F35: =F14*$B$33+F28*$B$34 | G35: =G14*$B$33+G28*$B$34 | H35: =H14*$B$33+H28*$B$34
A36: Blended revenue per analysis ($) | B36: =B15*$B$33+B29*$B$34 | C36: =C15*$B$33+C29*$B$34 | D36: =D15*$B$33+D29*$B$34 | E36: =E15*$B$33+E29*$B$34 | F36: =F15*$B$33+F29*$B$34 | G36: =G15*$B$33+G29*$B$34 | H36: =H15*$B$33+H29*$B$34
A37: Gross margin % — Blended | B37: =IFERROR((B36-B35)/B36,0) | C37: =IFERROR((C36-C35)/C36,0) | D37: =IFERROR((D36-D35)/D36,0) | E37: =IFERROR((E36-E35)/E36,0) | F37: =IFERROR((F36-F35)/F36,0) | G37: =IFERROR((G36-G35)/G36,0) | H37: =IFERROR((H36-H35)/H36,0)
A39: Notes:
A40: • 60s is the typical TikTok/Reels UGC length and the primary benchmark bucket.
A41: • Prompt and output token estimates are conservative — if actual prompts grow, edit Assumptions!B10-B14.
A42: • Infrastructure COGS assumes Vercel Pro + Neon — if self-hosted on bare EC2, will be lower.
A43: • Gemini pricing is volume-independent for SaaS; no enterprise discount assumed.
A44: • Re-analysis (chat on existing analysis) adds ~30-50% to LLM COGS per session if not cached.

Sheet Ryze Case
A1: Ryze as Design Partner — Monthly Economics
A3: Metric | B3: Value | C3: Unit | D3: Note
A4: Editors / creators at Ryze | B4: 55 | C4: people | D4: From user
A5: Analyses per editor per month | B5: 100 | C5: #/mo | D5: Assumption — tweak based on real usage
A6: Total analyses per month | B6: =B4*B5 | C6: #/mo
A7: Average video length (seconds) | B7: 60 | C7: sec | D7: TikTok/Reels median
A9: Scenario A — Flash only at $1/analysis
A10: COGS per analysis | B10: ='Per Analysis'!E14 | C10: $
A11: Revenue per analysis | B11: =Assumptions!B22*Assumptions!B23 | C11: $
A12: Monthly COGS | B12: =B6*B10 | C12: $/mo
A13: Monthly revenue (MRR from Ryze) | B13: =B6*B11 | C13: $/mo
A14: Gross profit (Ryze only) | B14: =B13-B12 | C14: $/mo
A15: Gross margin % | B15: =IFERROR(B14/B13,0) | C15: %
A17: Scenario B — Pro only at $3/analysis
A18: COGS per analysis | B18: ='Per Analysis'!E28 | C18: $
A19: Revenue per analysis | B19: =Assumptions!B22*Assumptions!B24 | C19: $
A20: Monthly COGS | B20: =B6*B18 | C20: $/mo
A21: Monthly revenue (MRR from Ryze) | B21: =B6*B19 | C21: $/mo
A22: Gross profit (Ryze only) | B22: =B21-B20 | C22: $/mo
A23: Gross margin % | B23: =IFERROR(B22/B21,0) | C23: %
A25: Scenario C — Blended 70/30 (recommended)
A26: COGS per analysis | B26: ='Per Analysis'!E35 | C26: $
A27: Revenue per analysis | B27: ='Per Analysis'!E36 | C27: $
A28: Monthly COGS | B28: =B6*B26 | C28: $/mo
A29: Monthly revenue (MRR from Ryze) | B29: =B6*B27 | C29: $/mo
A30: Gross profit (Ryze only) | B30: =B29-B28 | C30: $/mo
A31: Gross margin % | B31: =IFERROR(B30/B29,0) | C31: %
A33: Design partner reality (what Ryze actually pays)
A34: Design partner discount % | B34: 0.5 | C34: % | D34: Recommended 12-month DP discount
A35: Effective MRR from Ryze (Blended @ 50% off) | B35: =B29*(1-B34) | C35: $/mo
A36: Effective gross margin | B36: =IFERROR((B35-B28)/B35,0) | C36: %

Sheet Scaling
A1: Scaling — MRR and Margin at Brand Count
A3: Metric | B3: 10 brands | C3: 50 brands | D3: 100 brands | E3: 250 brands | F3: Note
A4: Avg editors per brand | B4: 8 | C4: 8 | D4: 8 | E4: 8 | F4: Industry avg DTC team
A5: Analyses per editor per month | B5: 60 | C5: 60 | D5: 60 | E5: 60 | F5: Conservative vs Ryze (100)
A6: Brand count | B6: 10 | C6: 50 | D6: 100 | E6: 250
A7: Total monthly analyses | B7: =B4*B5*B6 | C7: =C4*C5*C6 | D7: =D4*D5*D6 | E7: =E4*E5*E6
A8: Blended COGS / analysis | B8: ='Per Analysis'!E35 | C8: ='Per Analysis'!E35 | D8: ='Per Analysis'!E35 | E8: ='Per Analysis'!E35
A9: Blended revenue / analysis | B9: ='Per Analysis'!E36 | C9: ='Per Analysis'!E36 | D9: ='Per Analysis'!E36 | E9: ='Per Analysis'!E36
A10: Gross MRR | B10: =B7*B9 | C10: =C7*C9 | D10: =D7*D9 | E10: =E7*E9
A11: Monthly COGS (variable) | B11: =B7*B8 | C11: =C7*C8 | D11: =D7*D8 | E11: =E7*E8
A12: Monthly fixed overhead | B12: =Assumptions!B27+Assumptions!B28+Assumptions!B29+Assumptions!B30 | C12: =Assumptions!B27+Assumptions!B28+Assumptions!B29+Assumptions!B30 | D12: =Assumptions!B27+Assumptions!B28+Assumptions!B29+Assumptions!B30 | E12: =Assumptions!B27+Assumptions!B28+Assumptions!B29+Assumptions!B30
A13: Gross profit (Gross MRR − variable COGS) | B13: =B10-B11 | C13: =C10-C11 | D13: =D10-D11 | E13: =E10-E11
A14: Gross margin % | B14: =IFERROR(B13/B10,0) | C14: =IFERROR(C13/C10,0) | D14: =IFERROR(D13/D10,0) | E14: =IFERROR(E13/E10,0)
A15: Net (GP − fixed) | B15: =B13-B12 | C15: =C13-C12 | D15: =D13-D12 | E15: =E13-E12
A16: Net margin % | B16: =IFERROR(B15/B10,0) | C16: =IFERROR(C15/C10,0) | D16: =IFERROR(D15/D10,0) | E16: =IFERROR(E15/E10,0)
A17: Annual net (at this scale) | B17: =B15*12 | C17: =C15*12 | D17: =D15*12 | E17: =E15*12
A19: Notes:
A20: • Brand-count is steady-state assumption; real growth will have ramp.
A21: • Fixed overhead includes salaries — remove if bootstrapped founder-only.
A22: • Scaling past 100 brands likely requires CS headcount, adjust salaries upward.
A23: • Churn not modeled — industry SaaS benchmark is 3-7%/mo for SMB, plan for 5%.

Sheet Production Cost
A1: UGC Production Cost Context — What Editors Pay to Make the Video You Analyze
A3: Tier | B3: Low ($) | C3: High ($) | D3: Source / Note
A4: UGC creator — entry level | B4: 50 | C4: 150 | D4: Source: Influee, Billo, Collabstr 2025 rate guides
A5: UGC creator — mid-tier (most common) | B5: 150 | C5: 300 | D5: Source: Superscale, Designrevision 2025 (avg $185)
A6: UGC creator — premium | B6: 300 | C6: 500 | D6: Source: Popfly, Kristian Larsen UGC guides 2026
A7: Usage rights — additional (+%) | B7: 0.3 | C7: 1.5 | D7: Source: Billo — paid usage +30-50%, perpetual +100-150%
A8: In-house creator fully loaded (est.) | B8: 80 | C8: 200 | D8: Salary + equipment amortized; Ryze-style 55-editor model
A9: Agency-produced video | B9: 500 | C9: 5000 | D9: Source: Superside, inBeat — creative agency rates
A11: Analysis cost as % of production cost
A12: Reference production cost (mid-tier creator midpoint) | B12: =(B6+C6)/2 | C12: $
A13: Flash analysis COGS (60s video) | B13: ='Per Analysis'!E14 | C13: $
A14: Flash analysis price (1 credit, 60s video) | B14: =Assumptions!B22
A15: Analysis price as % of production cost | B15: =IFERROR(B14/B12,0) | D15: A $1 analysis is <1% of production — editor burns it without hesitation
A16: Pro analysis price (3 credits, 60s video) | B16: =Assumptions!B22*Assumptions!B24
A17: Pro analysis price as % of production cost | B17: =IFERROR(B16/B12,0) | D17: Still well under 5% — priced correctly for decision-grade analysis
A20: Decision framing: at $1-3/analysis, the question is never cost — it's whether the analysis is good enough to change behavior.
A22: • UGC market saw 44% YoY price drop 2024→2025 due to AI UGC flooding supply.
A23: • Ryze's 55-editor in-house model indicates fully loaded cost per video $80-200 (salary amortized).
A24: • Analysis cost should target <5% of production cost to feel 'free' to the editor.
A25: • Premium tier can justify higher price if it prevents ONE bad creative from running (avg $500-2000 wasted spend per flop).
